xnatjsession/__init__.py
xnatjsession-0.3.dist-info/LICENSE
xnatjsession-0.3.dist-info/METADATA
xnatjsession-0.3.dist-info/WHEEL
xnatjsession-0.3.dist-info/top_level.txt
xnatjsession-0.3.dist-info/RECORD
