Metadata-Version: 2.1
Name: xnatjsession
Version: 0.3
Summary: Utility functions for using XNAT JSESSION
Home-page: https://github.com/radiologics/docker-images
Author: Brian Holt
Author-email: beholt@radiologics.com
License: UNKNOWN
Platform: UNKNOWN
Classifier: Programming Language :: Python :: 3
Classifier: Programming Language :: Python :: 2
Requires-Python: >=2.6
Requires-Dist: requests (>=2.18.4)
